{
    "id": "quick",
    "symbol": "quick",
    "name": "Quickswap [OLD]",
    "web_slug": "quickswap-old",
    "asset_platform_id": "ethereum",
    "platforms": {
        "ethereum": "0x6c28aef8977c9b773996d0e8376d2ee379446f2f",
        "polygon-pos": "0x831753dd7087cac61ab5644b308642cc1c33dc13"
    },
    "detail_platforms": {
        "ethereum": {
            "decimal_place": 18,
            "contract_address": "0x6c28aef8977c9b773996d0e8376d2ee379446f2f"
        },
        "polygon-pos": {
            "decimal_place": 18,
            "contract_address": "0x831753dd7087cac61ab5644b308642cc1c33dc13"
        }
    },
    "block_time_in_minutes": 0,
    "hashing_algorithm": null,
    "categories": [
        "Decentralized Exchange (DEX)",
        "Exchange-based Tokens",
        "Decentralized Finance (DeFi)",
        "Yield Farming",
        "Automated Market Maker (AMM)",
        "Polygon Ecosystem",
        "Ethereum Ecosystem"
    ],
    "preview_listing": false,
    "public_notice": "Quickswap has redenominated to a 1:1000 ratio. New token page can be found <a href=\"https://www.coingecko.com/en/coins/quickswap\">Here</a>.<br>Read more at: https://quickswap-layer2.medium.com/how-to-convert-your-old-quick-to-new-quick-1000x-your-holdings-9443463290a4",
    "additional_notices": [],
    "localization": {
        "en": "Quickswap [OLD]",
        "de": "",
        "es": "",
        "fr": "",
        "it": "",
        "pl": "",
        "ro": "",
        "hu": "",
        "nl": "",
        "pt": "",
        "sv": "",
        "vi": "",
        "tr": "",
        "ru": "",
        "ja": "",
        "zh": "",
        "zh-tw": "",
        "ko": "",
        "ar": "",
        "th": "",
        "id": "",
        "cs": "",
        "da": "",
        "el": "",
        "hi": "",
        "no": "",
        "sk": "",
        "uk": "",
        "he": "",
        "fi": "",
        "bg": "",
        "hr": "",
        "lt": "",
        "sl": ""
    },
    "description": {
        "en": "QuickSwap is the leading DEX on Polygon PoS, Polygon zkEVM, & Dogechain, best known for it's blazing fast transaction speeds and near-zero gas fees. The DEX was launched in 2020 & provides DeFi features such as swaps, liquidity providing, farming, & staking.\r\n\r\nIt's also home to the DragonFi ecosystem, a powerful DeFi product suite that includes a decentralized Perpetual Exchange (QuickPerps), Gaming Hub, and much more.\r\n\r\n$QUICK (OLD) is the existing version of QuickSwap's native token - a token split took place in 2022 that redenominated it to New $QUICK at a 1:1000 ratio. The Old $QUICK token does not have any utility on the DEX, so users can convert to New $QUICK via QuickSwap's converter & stake in the Dragon's Lair to earn yield, in addition to farming the token to earn rewards.\r\n",
        "de": "",
        "es": "",
        "fr": "",
        "it": "",
        "pl": "",
        "ro": "",
        "hu": "",
        "nl": "",
        "pt": "",
        "sv": "",
        "vi": "",
        "tr": "",
        "ru": "",
        "ja": "",
        "zh": "",
        "zh-tw": "",
        "ko": "",
        "ar": "",
        "th": "",
        "id": "",
        "cs": "",
        "da": "",
        "el": "",
        "hi": "",
        "no": "",
        "sk": "",
        "uk": "",
        "he": "",
        "fi": "",
        "bg": "",
        "hr": "",
        "lt": "",
        "sl": ""
    },
    "links": {
        "homepage": [
            "https://quickswap.exchange/"
        ],
        "whitepaper": "",
        "blockchain_site": [
            "https://etherscan.io/token/0x6c28aef8977c9b773996d0e8376d2ee379446f2f",
            "https://platform.arkhamintelligence.com/explorer/token/quick",
            "https://ethplorer.io/address/0x6c28aef8977c9b773996d0e8376d2ee379446f2f",
            "https://polygonscan.com/token/0x831753dd7087cac61ab5644b308642cc1c33dc13"
        ],
        "official_forum_url": [],
        "chat_url": [
            "https://discord.gg/Bj2w4NujCh"
        ],
        "announcement_url": [
            "https://medium.com/@quickswap.layer2"
        ],
        "snapshot_url": null,
        "twitter_screen_name": "QuickswapDEX",
        "facebook_username": "",
        "bitcointalk_thread_identifier": null,
        "telegram_channel_identifier": "QuickSwapDEX",
        "subreddit_url": "https://www.reddit.com/r/QuickSwap/",
        "repos_url": {
            "github": [
                "https://github.com/QuickSwap/quickswap-core"
            ],
            "bitbucket": []
        }
    },
    "image": {
        "thumb": "https://coin-images.coingecko.com/coins/images/13970/thumb/quick.png?1696513704",
        "small": "https://coin-images.coingecko.com/coins/images/13970/small/quick.png?1696513704",
        "large": "https://coin-images.coingecko.com/coins/images/13970/large/quick.png?1696513704"
    },
    "country_origin": "",
    "genesis_date": null,
    "contract_address": "0x6c28aef8977c9b773996d0e8376d2ee379446f2f",
    "sentiment_votes_up_percentage": null,
    "sentiment_votes_down_percentage": null,
    "watchlist_portfolio_users": 23196,
    "market_cap_rank": 1176,
    "market_data": {
        "current_price": {
            "aed": 89.79,
            "ars": 28738,
            "aud": 37.93,
            "bch": 0.06841929,
            "bdt": 2980.09,
            "bhd": 9.24,
            "bmd": 24.45,
            "bnb": 0.04142503,
            "brl": 138.36,
            "btc": 0.00025574,
            "cad": 33.79,
            "chf": 20.22,
            "clp": 23214,
            "cny": 178.34,
            "czk": 538.97,
            "dkk": 161.45,
            "dot": 6.135563,
            "eos": 34.826592,
            "eth": 0.01335514,
            "eur": 21.63,
            "gbp": 18.43,
            "gel": 67.11,
            "hkd": 189.47,
            "huf": 8748.67,
            "idr": 402556,
            "ils": 88.47,
            "inr": 2066.4,
            "jpy": 3540.5,
            "krw": 34223,
            "kwd": 7.52,
            "lkr": 7342.2,
            "ltc": 0.28186925,
            "mmk": 51289,
            "mxn": 478.68,
            "myr": 104.39,
            "ngn": 39292,
            "nok": 254.54,
            "nzd": 41.07,
            "php": 1357.04,
            "pkr": 6891.52,
            "pln": 92.55,
            "rub": 2027.41,
            "sar": 91.68,
            "sek": 236.03,
            "sgd": 31.78,
            "sol": 0.16642918,
            "thb": 809.19,
            "try": 940.27,
            "twd": 750.9,
            "uah": 1017.23,
            "usd": 24.45,
            "vef": 2.45,
            "vnd": 635737,
            "xag": 0.762746,
            "xau": 0.00754206,
            "xdr": 17.61,
            "xlm": 90.516,
            "xrp": 11.122151,
            "yfi": 0.00462409,
            "zar": 449.67,
            "bits": 255.74,
            "link": 1.726674,
            "sats": 25574
        },
        "total_value_locked": {
            "btc": 1378,
            "usd": 131847400
        },
        "mcap_to_tvl_ratio": 0.14,
        "fdv_to_tvl_ratio": 0.19,
        "roi": null,
        "ath": {
            "aed": 5842.16,
            "ars": 148698,
            "aud": 2045.02,
            "bch": 1.731257,
            "bdt": 134875,
            "bhd": 599.64,
            "bmd": 1590.57,
            "bnb": 2.864664,
            "brl": 8491.11,
            "btc": 0.02924346,
            "cad": 1953.3,
            "chf": 1444.83,
            "clp": 1128353,
            "cny": 10290.84,
            "czk": 33988,
            "dkk": 9764.23,
            "dot": 43.764049,
            "eos": 254.299,
            "eth": 0.56996143,
            "eur": 1313.12,
            "gbp": 1140.83,
            "gel": 293.09,
            "hkd": 12350.06,
            "huf": 472881,
            "idr": 22970092,
            "ils": 5164.84,
            "inr": 117678,
            "jpy": 172989,
            "krw": 1767953,
            "kwd": 478.82,
            "lkr": 313294,
            "ltc": 5.99829,
            "mmk": 2477340,
            "mxn": 31866,
            "myr": 6530.09,
            "ngn": 650158,
            "nok": 13043.45,
            "nzd": 2194.26,
            "php": 76616,
            "pkr": 244153,
            "pln": 5999.65,
            "rub": 118525,
            "sar": 5964.87,
            "sek": 13335.65,
            "sgd": 1915.67,
            "thb": 49610,
            "try": 13087.92,
            "twd": 44385,
            "uah": 44145,
            "usd": 1590.57,
            "vef": 159.26,
            "vnd": 36698911,
            "xag": 61.2,
            "xau": 0.897162,
            "xdr": 1107.49,
            "xlm": 3077,
            "xrp": 1292,
            "yfi": 0.03245441,
            "zar": 22807,
            "bits": 29243,
            "link": 42.255152,
            "sats": 2924346
        },
        "ath_change_percentage": {
            "aed": -98.46276,
            "ars": -80.67052,
            "aud": -98.14516,
            "bch": -96.05131,
            "bdt": -97.7901,
            "bhd": -98.45908,
            "bmd": -98.46276,
            "bnb": -98.55412,
            "brl": -98.37024,
            "btc": -99.12559,
            "cad": -98.26986,
            "chf": -98.60039,
            "clp": -97.94235,
            "cny": -98.26672,
            "czk": -98.41396,
            "dkk": -98.34619,
            "dot": -85.97787,
            "eos": -86.3136,
            "eth": -97.65727,
            "eur": -98.35256,
            "gbp": -98.38446,
            "gel": -77.09975,
            "hkd": -98.46555,
            "huf": -98.14961,
            "idr": -98.24718,
            "ils": -98.28686,
            "inr": -98.24373,
            "jpy": -97.95299,
            "krw": -98.06393,
            "kwd": -98.42936,
            "lkr": -97.65605,
            "ltc": -95.30187,
            "mmk": -97.92931,
            "mxn": -98.49761,
            "myr": -98.40117,
            "ngn": -93.95559,
            "nok": -98.04822,
            "nzd": -98.12784,
            "php": -98.22848,
            "pkr": -97.1769,
            "pln": -98.45712,
            "rub": -98.28918,
            "sar": -98.46279,
            "sek": -98.22981,
            "sgd": -98.34099,
            "thb": -98.36863,
            "try": -92.81456,
            "twd": -98.30792,
            "uah": -97.69535,
            "usd": -98.46276,
            "vef": -98.46276,
            "vnd": -98.2674,
            "xag": -98.75346,
            "xau": -99.1592,
            "xdr": -98.41002,
            "xlm": -97.05866,
            "xrp": -99.13929,
            "yfi": -85.75085,
            "zar": -98.028,
            "bits": -99.12559,
            "link": -95.91449,
            "sats": -99.12559
        },
        "ath_date": {
            "aed": "2021-04-30T06:58:38.492Z",
            "ars": "2021-04-30T06:58:38.492Z",
            "aud": "2021-04-30T06:58:38.492Z",
            "bch": "2021-04-30T06:58:38.492Z",
            "bdt": "2021-04-30T06:58:38.492Z",
            "bhd": "2021-04-30T06:58:38.492Z",
            "bmd": "2021-04-30T06:58:38.492Z",
            "bnb": "2021-05-20T15:57:56.500Z",
            "brl": "2021-04-30T06:58:38.492Z",
            "btc": "2021-04-30T06:58:38.492Z",
            "cad": "2021-04-30T06:58:38.492Z",
            "chf": "2021-04-30T06:58:38.492Z",
            "clp": "2021-04-30T06:58:38.492Z",
            "cny": "2021-04-30T06:58:38.492Z",
            "czk": "2021-04-30T06:58:38.492Z",
            "dkk": "2021-04-30T06:58:38.492Z",
            "dot": "2021-04-30T06:58:38.492Z",
            "eos": "2021-04-30T06:58:38.492Z",
            "eth": "2021-04-30T06:58:38.492Z",
            "eur": "2021-04-30T06:58:38.492Z",
            "gbp": "2021-04-30T06:58:38.492Z",
            "gel": "2024-03-02T21:51:44.792Z",
            "hkd": "2021-04-30T06:58:38.492Z",
            "huf": "2021-04-30T06:58:38.492Z",
            "idr": "2021-04-30T06:58:38.492Z",
            "ils": "2021-04-30T06:58:38.492Z",
            "inr": "2021-04-30T06:58:38.492Z",
            "jpy": "2021-04-30T06:58:38.492Z",
            "krw": "2021-04-30T06:58:38.492Z",
            "kwd": "2021-04-30T06:58:38.492Z",
            "lkr": "2021-04-30T06:58:38.492Z",
            "ltc": "2021-04-30T06:58:38.492Z",
            "mmk": "2021-04-30T06:58:38.492Z",
            "mxn": "2021-04-30T06:58:38.492Z",
            "myr": "2021-04-30T06:58:38.492Z",
            "ngn": "2021-04-30T06:58:38.492Z",
            "nok": "2021-04-30T06:58:38.492Z",
            "nzd": "2021-04-30T06:58:38.492Z",
            "php": "2021-04-30T06:58:38.492Z",
            "pkr": "2021-04-30T06:58:38.492Z",
            "pln": "2021-04-30T06:58:38.492Z",
            "rub": "2021-04-30T06:58:38.492Z",
            "sar": "2021-04-30T06:58:38.492Z",
            "sek": "2021-04-30T06:58:38.492Z",
            "sgd": "2021-05-01T00:00:00.000Z",
            "thb": "2021-04-30T06:58:38.492Z",
            "try": "2021-04-30T07:14:34.851Z",
            "twd": "2021-04-30T06:58:38.492Z",
            "uah": "2021-04-30T06:58:38.492Z",
            "usd": "2021-04-30T06:58:38.492Z",
            "vef": "2021-04-30T06:58:38.492Z",
            "vnd": "2021-04-30T06:58:38.492Z",
            "xag": "2021-04-30T06:58:38.492Z",
            "xau": "2021-04-30T06:58:38.492Z",
            "xdr": "2021-04-30T06:58:38.492Z",
            "xlm": "2021-04-30T06:58:38.492Z",
            "xrp": "2021-03-01T12:58:57.445Z",
            "yfi": "2021-04-30T06:58:38.492Z",
            "zar": "2021-04-30T07:14:34.851Z",
            "bits": "2021-04-30T06:58:38.492Z",
            "link": "2021-04-30T06:58:38.492Z",
            "sats": "2021-04-30T06:58:38.492Z"
        },
        "atl": {
            "aed": 0.093602,
            "ars": 13.34,
            "aud": 0.03930036,
            "bch": 7.67e-05,
            "bdt": 2.99,
            "bhd": 0.00960458,
            "bmd": 0.02548392,
            "bnb": 4.997e-05,
            "brl": 0.144711,
            "btc": 4.41015e-07,
            "cad": 0.03525089,
            "chf": 0.02166409,
            "clp": 24.25,
            "cny": 0.181698,
            "czk": 0.588245,
            "dkk": 0.173599,
            "dot": 0.00552539,
            "eos": 0.05315489,
            "eth": 1.028e-05,
            "eur": 0.02326346,
            "gbp": 0.01996698,
            "gel": 0.068679,
            "hkd": 0.198473,
            "huf": 9.22,
            "idr": 411.51,
            "ils": 0.097279,
            "inr": 2.14,
            "jpy": 3.66,
            "krw": 34.89,
            "kwd": 0.0077831,
            "lkr": 7.65,
            "ltc": 0.00040265,
            "mmk": 53.47,
            "mxn": 0.496017,
            "myr": 0.112766,
            "ngn": 30.77,
            "nok": 0.277751,
            "nzd": 0.04281701,
            "php": 1.48,
            "pkr": 7.11,
            "pln": 0.100017,
            "rub": 2.16,
            "sar": 0.095672,
            "sek": 0.269078,
            "sgd": 0.03376602,
            "thb": 0.903405,
            "try": 0.849598,
            "twd": 0.833605,
            "uah": 1.049,
            "usd": 0.02548392,
            "vef": 0.00255171,
            "vnd": 639.58,
            "xag": 0.00092689,
            "xau": 1.058e-05,
            "xdr": 0.01916906,
            "xlm": 0.25835243,
            "xrp": 0.04296594,
            "yfi": 5.24e-06,
            "zar": 0.472687,
            "bits": 0.441015,
            "link": 0.0025562,
            "sats": 44.1
        },
        "atl_change_percentage": {
            "aed": 95846.26247,
            "ars": 215283.66285,
            "aud": 96417.8352,
            "bch": 89026.4094,
            "bdt": 99498.61542,
            "bhd": 96104.6561,
            "bmd": 95846.26247,
            "bnb": 82791.36901,
            "brl": 95527.95525,
            "btc": 57881.5216,
            "cad": 95769.27019,
            "chf": 93243.40177,
            "clp": 95650.62832,
            "cny": 98067.99461,
            "czk": 91538.84163,
            "dkk": 92920.09592,
            "dot": 110962.84716,
            "eos": 65377.16855,
            "eth": 129735.98033,
            "eur": 92890.94253,
            "gbp": 92205.01834,
            "gel": 97626.34156,
            "hkd": 95381.63271,
            "huf": 94755.29011,
            "idr": 97740.94761,
            "ils": 90856.17919,
            "inr": 96420.00764,
            "jpy": 96674.77709,
            "krw": 98011.31827,
            "kwd": 96526.4049,
            "lkr": 95834.15917,
            "ltc": 69888.99191,
            "mmk": 95846.26247,
            "mxn": 96421.03394,
            "myr": 92485.43294,
            "ngn": 127635.7206,
            "nok": 91557.54548,
            "nzd": 95843.42442,
            "php": 91854.0202,
            "pkr": 96843.3044,
            "pln": 92451.69822,
            "rub": 93649.77516,
            "sar": 95741.06964,
            "sek": 87631.50434,
            "sgd": 94021.89802,
            "thb": 89485.93196,
            "try": 110590.48345,
            "twd": 89993.74578,
            "uah": 96892.9468,
            "usd": 95846.26247,
            "vef": 95846.26247,
            "vnd": 99316.52529,
            "xag": 82204.96587,
            "xau": 71179.84549,
            "xdr": 91761.47792,
            "xlm": 34927.45999,
            "xrp": 25777.71648,
            "yfi": 88232.86309,
            "zar": 95047.32188,
            "bits": 57881.5216,
            "link": 67435.39723,
            "sats": 57881.5216
        },
        "atl_date": {
            "aed": "2024-08-05T19:21:30.349Z",
            "ars": "2023-08-11T03:56:13.647Z",
            "aud": "2024-08-05T19:21:30.349Z",
            "bch": "2024-08-10T10:21:07.275Z",
            "bdt": "2024-08-05T19:21:30.349Z",
            "bhd": "2024-08-05T19:21:30.349Z",
            "bmd": "2024-08-05T19:21:30.349Z",
            "bnb": "2024-08-17T20:39:48.266Z",
            "brl": "2024-08-08T01:01:08.722Z",
            "btc": "2024-08-09T20:59:08.597Z",
            "cad": "2024-08-05T19:21:30.349Z",
            "chf": "2024-08-05T19:21:30.349Z",
            "clp": "2024-08-08T01:01:08.722Z",
            "cny": "2024-08-05T19:21:30.349Z",
            "czk": "2024-08-05T19:21:30.349Z",
            "dkk": "2024-08-05T19:21:30.349Z",
            "dot": "2024-08-09T18:49:50.311Z",
            "eos": "2024-08-17T06:10:45.914Z",
            "eth": "2024-08-09T22:00:02.838Z",
            "eur": "2024-08-05T19:21:30.349Z",
            "gbp": "2024-08-05T19:21:30.349Z",
            "gel": "2024-08-05T19:21:30.349Z",
            "hkd": "2024-08-05T19:21:30.349Z",
            "huf": "2024-08-05T19:21:30.349Z",
            "idr": "2024-08-08T01:01:08.722Z",
            "ils": "2024-08-08T01:01:08.722Z",
            "inr": "2024-08-05T19:21:30.349Z",
            "jpy": "2024-08-05T19:21:30.349Z",
            "krw": "2024-08-05T19:21:30.349Z",
            "kwd": "2024-08-05T19:21:30.349Z",
            "lkr": "2024-08-05T19:21:30.349Z",
            "ltc": "2024-08-17T09:10:06.886Z",
            "mmk": "2024-08-05T19:21:30.349Z",
            "mxn": "2024-08-08T01:01:08.722Z",
            "myr": "2024-08-05T19:21:30.349Z",
            "ngn": "2023-08-18T21:09:48.307Z",
            "nok": "2024-08-08T01:01:08.722Z",
            "nzd": "2024-08-08T01:01:08.722Z",
            "php": "2024-08-05T19:21:30.349Z",
            "pkr": "2024-08-05T19:21:30.349Z",
            "pln": "2024-08-05T19:21:30.349Z",
            "rub": "2024-08-05T19:21:30.349Z",
            "sar": "2024-08-05T19:21:30.349Z",
            "sek": "2024-08-08T01:01:08.722Z",
            "sgd": "2024-08-05T19:21:30.349Z",
            "thb": "2024-08-05T19:21:30.349Z",
            "try": "2024-08-05T19:21:30.349Z",
            "twd": "2024-08-05T19:21:30.349Z",
            "uah": "2024-08-05T19:21:30.349Z",
            "usd": "2024-08-05T19:21:30.349Z",
            "vef": "2024-08-05T19:21:30.349Z",
            "vnd": "2024-08-05T19:21:30.349Z",
            "xag": "2024-08-17T06:10:45.914Z",
            "xau": "2024-08-05T19:21:30.349Z",
            "xdr": "2024-08-05T19:21:30.349Z",
            "xlm": "2024-08-08T01:40:48.343Z",
            "xrp": "2024-08-08T03:40:24.446Z",
            "yfi": "2024-08-05T18:35:54.990Z",
            "zar": "2024-08-08T01:01:08.722Z",
            "bits": "2024-08-09T20:59:08.597Z",
            "link": "2024-08-10T01:20:56.093Z",
            "sats": "2024-08-09T20:59:08.597Z"
        },
        "market_cap": {
            "aed": 67722560,
            "ars": 21674265891,
            "aud": 28603701,
            "bch": 51565,
            "bdt": 2247611363,
            "bhd": 6967754,
            "bmd": 18437942,
            "bnb": 31237,
            "brl": 104353219,
            "btc": 192.841,
            "cad": 25484001,
            "chf": 15249026,
            "clp": 17507930375,
            "cny": 134504786,
            "czk": 406495772,
            "dkk": 121770381,
            "dot": 4628006,
            "eos": 26255194,
            "eth": 10071,
            "eur": 16312969,
            "gbp": 13898115,
            "gel": 50612150,
            "hkd": 142902346,
            "huf": 6598321964,
            "idr": 303611019652,
            "ils": 66722044,
            "inr": 1558494689,
            "jpy": 2670275032,
            "krw": 25811274754,
            "kwd": 5671087,
            "lkr": 5537552693,
            "ltc": 212613,
            "mmk": 38682801938,
            "mxn": 361024138,
            "myr": 78730012,
            "ngn": 29634022321,
            "nok": 191974006,
            "nzd": 30977734,
            "php": 1023490169,
            "pkr": 5197642450,
            "pln": 69803540,
            "rub": 1529087592,
            "sar": 69143812,
            "sek": 178012797,
            "sgd": 23965618,
            "sol": 125523,
            "thb": 610295874,
            "try": 709156412,
            "twd": 566334271,
            "uah": 767201303,
            "usd": 18437942,
            "vef": 1846191,
            "vnd": 479478677025,
            "xag": 575270,
            "xau": 5688.29,
            "xdr": 13278600,
            "xlm": 68250893,
            "xrp": 8385547,
            "yfi": 3488,
            "zar": 339147502,
            "bits": 192841435,
            "link": 1302147,
            "sats": 19284143544
        },
        "market_cap_rank": 1176,
        "fully_diluted_valuation": {
            "aed": 89802788,
            "ars": 28740931960,
            "aud": 37929636,
            "bch": 68377,
            "bdt": 2980421371,
            "bhd": 9239516,
            "bmd": 24449439,
            "bnb": 41421,
            "brl": 138376487,
            "btc": 255.715,
            "cad": 33792791,
            "chf": 20220810,
            "clp": 23216206639,
            "cny": 178358654,
            "czk": 539029436,
            "dkk": 161472331,
            "dot": 6136919,
            "eos": 34815424,
            "eth": 13355,
            "eur": 21631641,
            "gbp": 18429449,
            "gel": 67113709,
            "hkd": 189494151,
            "huf": 8749635332,
            "idr": 402600194259,
            "ils": 88476063,
            "inr": 2066625465,
            "jpy": 3540890077,
            "krw": 34226768981,
            "kwd": 7520085,
            "lkr": 7343013413,
            "ltc": 281933,
            "mmk": 51294922011,
            "mxn": 478732255,
            "myr": 104399102,
            "ngn": 39295883123,
            "nok": 254565109,
            "nzd": 41077697,
            "php": 1357188357,
            "pkr": 6892279017,
            "pln": 92562249,
            "rub": 2027630493,
            "sar": 91687424,
            "sek": 236051994,
            "sgd": 31779356,
            "thb": 809276415,
            "try": 940369390,
            "twd": 750981594,
            "uah": 1017339205,
            "usd": 24449439,
            "vef": 2448122,
            "vnd": 635807648663,
            "xag": 762830,
            "xau": 7542.9,
            "xdr": 17607948,
            "xlm": 90503377,
            "xrp": 11119566,
            "yfi": 4625,
            "zar": 449722972,
            "bits": 255715354,
            "link": 1726699,
            "sats": 25571535401
        },
        "market_cap_fdv_ratio": 0.75,
        "total_volume": {
            "aed": 24061,
            "ars": 7700478,
            "aud": 10162.38,
            "bch": 18.333415,
            "bdt": 798536,
            "bhd": 2475.52,
            "bmd": 6550.67,
            "bnb": 11.100119,
            "brl": 37075,
            "btc": 0.06852843,
            "cad": 9054.01,
            "chf": 5417.71,
            "clp": 6220254,
            "cny": 47787,
            "czk": 144421,
            "dkk": 43263,
            "dot": 1644,
            "eos": 9332,
            "eth": 3.578601,
            "eur": 5795.71,
            "gbp": 4937.75,
            "gel": 17981.59,
            "hkd": 50771,
            "huf": 2344266,
            "idr": 107867558,
            "ils": 23705,
            "inr": 553705,
            "jpy": 948701,
            "krw": 9170284,
            "kwd": 2014.84,
            "lkr": 1967393,
            "ltc": 75.529,
            "mmk": 13743307,
            "mxn": 128265,
            "myr": 27971,
            "ngn": 10528437,
            "nok": 68205,
            "nzd": 11005.83,
            "php": 363628,
            "pkr": 1846629,
            "pln": 24800,
            "rub": 543257,
            "sar": 24566,
            "sek": 63245,
            "sgd": 8514.55,
            "sol": 44.59583,
            "thb": 216827,
            "try": 251951,
            "twd": 201208,
            "uah": 272573,
            "usd": 6550.67,
            "vef": 655.92,
            "vnd": 170350187,
            "xag": 204.38,
            "xau": 2.02,
            "xdr": 4717.65,
            "xlm": 24254,
            "xrp": 2980,
            "yfi": 1.239056,
            "zar": 120493,
            "bits": 68528,
            "link": 462.674,
            "sats": 6852843
        },
        "high_24h": {
            "aed": 92.05,
            "ars": 29371,
            "aud": 38.88,
            "bch": 0.06833575,
            "bdt": 3054.85,
            "bhd": 9.44,
            "bmd": 25.06,
            "bnb": 0.0418449,
            "brl": 141.83,
            "btc": 0.00025977,
            "cad": 34.63,
            "chf": 20.73,
            "clp": 23711,
            "cny": 182.81,
            "czk": 552.49,
            "dkk": 165.5,
            "dot": 6.160842,
            "eos": 34.816806,
            "eth": 0.01363816,
            "eur": 22.17,
            "gbp": 18.89,
            "gel": 68.79,
            "hkd": 194.22,
            "huf": 8972.99,
            "idr": 412830,
            "ils": 89.9,
            "inr": 2120.84,
            "jpy": 3631.19,
            "krw": 35080,
            "kwd": 7.68,
            "lkr": 7526.39,
            "ltc": 0.28872994,
            "mmk": 52576,
            "mxn": 490.69,
            "myr": 107.01,
            "ngn": 40189,
            "nok": 260.92,
            "nzd": 42.1,
            "php": 1394.92,
            "pkr": 7064.4,
            "pln": 94.86,
            "rub": 2072.44,
            "sar": 93.98,
            "sek": 241.95,
            "sgd": 32.57,
            "thb": 829.49,
            "try": 966.73,
            "twd": 769.74,
            "uah": 1042.74,
            "usd": 25.06,
            "vef": 2.51,
            "vnd": 651685,
            "xag": 0.78188,
            "xau": 0.00773126,
            "xdr": 18.05,
            "xlm": 91.919,
            "xrp": 11.326765,
            "yfi": 0.00465015,
            "zar": 460.95,
            "bits": 259.77,
            "link": 1.738261,
            "sats": 25977
        },
        "low_24h": {
            "aed": 88.64,
            "ars": 28367,
            "aud": 37.44,
            "bch": 0.06632661,
            "bdt": 2941.69,
            "bhd": 9.12,
            "bmd": 24.13,
            "bnb": 0.04036994,
            "brl": 136.58,
            "btc": 0.00025209,
            "cad": 33.35,
            "chf": 19.96,
            "clp": 22914,
            "cny": 176.04,
            "czk": 532.02,
            "dkk": 159.37,
            "dot": 5.997206,
            "eos": 32.817944,
            "eth": 0.01316442,
            "eur": 21.35,
            "gbp": 18.19,
            "gel": 66.24,
            "hkd": 187.03,
            "huf": 8635.92,
            "idr": 397368,
            "ils": 86.91,
            "inr": 2039.77,
            "jpy": 3494.87,
            "krw": 33782,
            "kwd": 7.42,
            "lkr": 7247.58,
            "ltc": 0.28056844,
            "mmk": 50628,
            "mxn": 472.51,
            "myr": 103.04,
            "ngn": 38785,
            "nok": 251.26,
            "nzd": 40.54,
            "php": 1339.55,
            "pkr": 6802.7,
            "pln": 91.36,
            "rub": 2001.28,
            "sar": 90.5,
            "sek": 232.98,
            "sgd": 31.37,
            "thb": 798.76,
            "try": 928.15,
            "twd": 741.22,
            "uah": 1004.12,
            "usd": 24.13,
            "vef": 2.42,
            "vnd": 627544,
            "xag": 0.752916,
            "xau": 0.00744487,
            "xdr": 17.38,
            "xlm": 89.221,
            "xrp": 10.9982,
            "yfi": 0.00446443,
            "zar": 443.88,
            "bits": 252.09,
            "link": 1.700635,
            "sats": 25209
        },
        "price_change_24h": -0.60864452214446,
        "price_change_percentage_24h": -2.4292,
        "price_change_percentage_7d": -4.3474,
        "price_change_percentage_14d": -9.01495,
        "price_change_percentage_30d": -4.6637,
        "price_change_percentage_60d": 5.40777,
        "price_change_percentage_200d": -39.52391,
        "price_change_percentage_1y": -60.51336,
        "market_cap_change_24h": -364990.39248263,
        "market_cap_change_percentage_24h": -1.94114,
        "price_change_24h_in_currency": {
            "aed": -2.2368040990920974,
            "ars": -627.7548094018821,
            "aud": -0.9442206794288239,
            "bch": 0.00069055,
            "bdt": -74.19463395920957,
            "bhd": -0.20314921801468522,
            "bmd": -0.6086445221444663,
            "bnb": -0.000415253512073013,
            "brl": -3.444745401981038,
            "btc": -4.024724601915e-06,
            "cad": -0.8387324877710327,
            "chf": -0.503777903623245,
            "clp": -492.5078294310915,
            "cny": -4.4400617890438525,
            "czk": -13.418603186362475,
            "dkk": -4.019693537446045,
            "dot": 0.07859806,
            "eos": 0.99309859,
            "eth": -0.000283013260838261,
            "eur": -0.5384982409673142,
            "gbp": -0.45878285061301227,
            "gel": -1.6707292132865632,
            "hkd": -4.706820841063973,
            "huf": -222.66135964831483,
            "idr": -10197.876515103853,
            "ils": -1.416060360287915,
            "inr": -54.05235125242234,
            "jpy": -90.0259530559415,
            "krw": -850.8529393019926,
            "kwd": -0.16372816034011972,
            "lkr": -182.7970358808061,
            "ltc": -0.005097930232608905,
            "mmk": -1276.9362074590754,
            "mxn": -11.917564674494429,
            "myr": -2.598912109556892,
            "ngn": -890.0247274980502,
            "nok": -6.337145900115928,
            "nzd": -1.022588530811099,
            "php": -37.61938206539253,
            "pkr": -171.576450133889,
            "pln": -2.289813483360902,
            "rub": -44.64912002511983,
            "sar": -2.285248623284218,
            "sek": -5.876280267948147,
            "sgd": -0.7911155412388489,
            "sol": -0.002127560991781186,
            "thb": -20.146133682981826,
            "try": -26.28597159450112,
            "twd": -18.694941940188073,
            "uah": -25.325650483513982,
            "usd": -0.6086445221444663,
            "vef": -0.06094357600232536,
            "vnd": -15827.800798366545,
            "xag": -0.018989903857154378,
            "xau": -0.000187772921526791,
            "xdr": -0.43833239466895435,
            "xlm": -1.142703105521477,
            "xrp": -0.19813825016907316,
            "yfi": 9.46e-05,
            "zar": -11.19540734032529,
            "bits": -4.024724601915409,
            "link": -0.002821624257379751,
            "sats": -402.4724601915368
        },
        "price_change_percentage_1h_in_currency": {
            "aed": 0.37213,
            "ars": 0.37213,
            "aud": 0.37213,
            "bch": 0.53406,
            "bdt": 0.37213,
            "bhd": 0.37213,
            "bmd": 0.37213,
            "bnb": 0.36129,
            "brl": 0.37213,
            "btc": 0.33583,
            "cad": 0.37213,
            "chf": 0.37213,
            "clp": 0.37213,
            "cny": 0.37213,
            "czk": 0.37213,
            "dkk": 0.37213,
            "dot": 0.20694,
            "eos": 0.17687,
            "eth": 0.22294,
            "eur": 0.37213,
            "gbp": 0.37213,
            "gel": 0.37213,
            "hkd": 0.37213,
            "huf": 0.37213,
            "idr": 0.37213,
            "ils": 0.37213,
            "inr": 0.37213,
            "jpy": 0.37213,
            "krw": 0.37213,
            "kwd": 0.37213,
            "lkr": 0.37213,
            "ltc": -0.04575,
            "mmk": 0.37213,
            "mxn": 0.37213,
            "myr": 0.37213,
            "ngn": 0.37213,
            "nok": 0.37213,
            "nzd": 0.37213,
            "php": 0.37213,
            "pkr": 0.37213,
            "pln": 0.37213,
            "rub": 0.37213,
            "sar": 0.37213,
            "sek": 0.37213,
            "sgd": 0.37213,
            "sol": -0.17626,
            "thb": 0.37213,
            "try": 0.37213,
            "twd": 0.37213,
            "uah": 0.37213,
            "usd": 0.37213,
            "vef": 0.37213,
            "vnd": 0.37213,
            "xag": 0.37213,
            "xau": 0.37213,
            "xdr": 0.37213,
            "xlm": -0.11523,
            "xrp": -0.05657,
            "yfi": -0.56046,
            "zar": 0.37213,
            "bits": 0.33583,
            "link": 0.17203,
            "sats": 0.33583
        },
        "price_change_percentage_24h_in_currency": {
            "aed": -2.43052,
            "ars": -2.13773,
            "aud": -2.4292,
            "bch": 1.01957,
            "bdt": -2.4292,
            "bhd": -2.15163,
            "bmd": -2.4292,
            "bnb": -0.99247,
            "brl": -2.4292,
            "btc": -1.54935,
            "cad": -2.42214,
            "chf": -2.43108,
            "clp": -2.07755,
            "cny": -2.4292,
            "czk": -2.4292,
            "dkk": -2.4292,
            "dot": 1.29765,
            "eos": 2.93525,
            "eth": -2.07516,
            "eur": -2.4292,
            "gbp": -2.4292,
            "gel": -2.4292,
            "hkd": -2.42395,
            "huf": -2.48192,
            "idr": -2.47069,
            "ils": -1.57546,
            "inr": -2.5491,
            "jpy": -2.47969,
            "krw": -2.42589,
            "kwd": -2.13105,
            "lkr": -2.4292,
            "ltc": -1.77649,
            "mmk": -2.4292,
            "mxn": -2.4292,
            "myr": -2.4292,
            "ngn": -2.21501,
            "nok": -2.4292,
            "nzd": -2.4292,
            "php": -2.69739,
            "pkr": -2.4292,
            "pln": -2.41435,
            "rub": -2.15482,
            "sar": -2.43208,
            "sek": -2.4292,
            "sgd": -2.4292,
            "sol": -1.26222,
            "thb": -2.4292,
            "try": -2.71956,
            "twd": -2.4292,
            "uah": -2.4292,
            "usd": -2.4292,
            "vef": -2.4292,
            "vnd": -2.4292,
            "xag": -2.4292,
            "xau": -2.4292,
            "xdr": -2.4292,
            "xlm": -1.2467,
            "xrp": -1.75029,
            "yfi": 2.08862,
            "zar": -2.4292,
            "bits": -1.54935,
            "link": -0.16315,
            "sats": -1.54935
        },
        "price_change_percentage_7d_in_currency": {
            "aed": -4.3474,
            "ars": -3.37414,
            "aud": -4.89607,
            "bch": -5.959,
            "bdt": -4.02759,
            "bhd": -4.08853,
            "bmd": -4.3474,
            "bnb": -2.66647,
            "brl": -4.86345,
            "btc": -5.95103,
            "cad": -4.79513,
            "chf": -4.49221,
            "clp": -2.85269,
            "cny": -4.25159,
            "czk": -4.04885,
            "dkk": -3.83431,
            "dot": -0.8922,
            "eos": -8.7377,
            "eth": -6.06897,
            "eur": -3.8147,
            "gbp": -4.01224,
            "gel": -4.08534,
            "hkd": -4.45465,
            "huf": -4.1018,
            "idr": -6.26772,
            "ils": -4.48713,
            "inr": -5.30886,
            "jpy": -3.58175,
            "krw": -6.90525,
            "kwd": -3.9762,
            "lkr": -4.12209,
            "ltc": -4.03247,
            "mmk": -4.3474,
            "mxn": -3.97124,
            "myr": -6.62172,
            "ngn": -4.44072,
            "nok": -4.58109,
            "nzd": -4.12239,
            "php": -5.59737,
            "pkr": -4.02421,
            "pln": -3.67022,
            "rub": -3.57496,
            "sar": -4.3692,
            "sek": -4.63779,
            "sgd": -5.38836,
            "sol": -2.89818,
            "thb": -5.51771,
            "try": -4.24782,
            "twd": -9.74024,
            "uah": -4.82541,
            "usd": -4.3474,
            "vef": -4.3474,
            "vnd": -4.40746,
            "xag": -1.17892,
            "xau": -2.07147,
            "xdr": -4.18495,
            "xlm": 1.30236,
            "xrp": -2.57851,
            "yfi": 11.12776,
            "zar": -5.85473,
            "bits": -5.95103,
            "link": -1.53807,
            "sats": -5.95103
        },
        "price_change_percentage_14d_in_currency": {
            "aed": -9.01495,
            "ars": -6.01227,
            "aud": -9.82454,
            "bch": -14.76222,
            "bdt": -8.66026,
            "bhd": -8.77088,
            "bmd": -9.01495,
            "bnb": -8.96946,
            "brl": -11.33813,
            "btc": -19.45432,
            "cad": -9.14444,
            "chf": -8.06294,
            "clp": -10.71682,
            "cny": -9.02492,
            "czk": -8.98324,
            "dkk": -8.47653,
            "dot": -11.75432,
            "eos": -15.74389,
            "eth": -21.43369,
            "eur": -8.4532,
            "gbp": -9.06983,
            "gel": -9.21339,
            "hkd": -9.16835,
            "huf": -9.3266,
            "idr": -11.16096,
            "ils": -10.6771,
            "inr": -9.92823,
            "jpy": -7.4609,
            "krw": -10.20102,
            "kwd": -8.66037,
            "lkr": -8.38772,
            "ltc": -19.89225,
            "mmk": -9.01495,
            "mxn": -9.65562,
            "myr": -11.85339,
            "ngn": -8.78507,
            "nok": -9.54145,
            "nzd": -8.68395,
            "php": -10.91586,
            "pkr": -8.52609,
            "pln": -8.44343,
            "rub": -8.17648,
            "sar": -9.06163,
            "sek": -8.6913,
            "sgd": -9.77538,
            "thb": -9.71574,
            "try": -7.95802,
            "twd": -14.07098,
            "uah": -8.31149,
            "usd": -9.01495,
            "vef": -9.01495,
            "vnd": -8.59888,
            "xag": -8.0088,
            "xau": -6.82534,
            "xdr": -8.75191,
            "xlm": -18.42295,
            "xrp": -14.78018,
            "yfi": -21.33614,
            "zar": -11.0797,
            "bits": -19.45432,
            "link": -15.51858,
            "sats": -19.45432
        },
        "price_change_percentage_30d_in_currency": {
            "aed": -4.66448,
            "ars": 4.41946,
            "aud": -10.08093,
            "bch": -19.53485,
            "bdt": -4.34114,
            "bhd": -4.42014,
            "bmd": -4.6637,
            "bnb": -3.70718,
            "brl": -6.94579,
            "btc": -17.07917,
            "cad": -7.17749,
            "chf": -7.96219,
            "clp": -6.13949,
            "cny": -4.70028,
            "czk": -8.3402,
            "dkk": -7.27518,
            "dot": -2.02217,
            "eos": 11.39543,
            "eth": -5.9601,
            "eur": -7.32063,
            "gbp": -6.96809,
            "gel": -5.69436,
            "hkd": -4.96254,
            "huf": -7.69192,
            "idr": -6.2485,
            "ils": -7.83907,
            "inr": -5.85541,
            "jpy": -5.45362,
            "krw": -8.58601,
            "kwd": -4.67238,
            "lkr": -3.57369,
            "ltc": -7.8697,
            "mmk": -4.6637,
            "mxn": -8.7569,
            "myr": -8.25197,
            "ngn": 0.09564,
            "nok": -7.35996,
            "nzd": -9.93597,
            "php": -7.79478,
            "pkr": -4.1816,
            "pln": -6.87956,
            "rub": -7.25304,
            "sar": -4.71746,
            "sek": -8.13495,
            "sgd": -7.63477,
            "thb": -8.44452,
            "try": -3.53253,
            "twd": -11.63867,
            "uah": -3.9103,
            "usd": -4.6637,
            "vef": -4.6637,
            "vnd": -3.93023,
            "xag": -10.96972,
            "xau": -10.41605,
            "xdr": -8.72628,
            "xlm": -8.05902,
            "xrp": -7.46357,
            "yfi": -13.69067,
            "zar": -7.69397,
            "bits": -17.07917,
            "link": -14.23571,
            "sats": -17.07917
        },
        "price_change_percentage_60d_in_currency": {
            "aed": 5.41781,
            "ars": 16.53231,
            "aud": 3.30387,
            "bch": 11.90228,
            "bdt": 5.90792,
            "bhd": 5.67426,
            "bmd": 5.40777,
            "bnb": 5.30008,
            "brl": 1.34137,
            "btc": -2.32783,
            "cad": 1.4393,
            "chf": -1.7732,
            "clp": 6.16467,
            "cny": 6.03862,
            "czk": 0.20618,
            "dkk": 0.50174,
            "dot": 14.99157,
            "eos": -19.65893,
            "eth": 25.11661,
            "eur": 0.43446,
            "gbp": 2.23905,
            "gel": 3.70764,
            "hkd": 5.12084,
            "huf": 1.95093,
            "idr": 6.58046,
            "ils": 5.28909,
            "inr": 2.54097,
            "jpy": 2.86258,
            "krw": 2.26001,
            "kwd": 5.14284,
            "lkr": 7.3399,
            "ltc": 23.58722,
            "mmk": 5.40777,
            "mxn": 1.17764,
            "myr": 1.61219,
            "ngn": 13.28593,
            "nok": 0.31099,
            "nzd": 1.18137,
            "php": 2.26484,
            "pkr": 6.30726,
            "pln": 3.4131,
            "rub": -2.50922,
            "sar": 5.39526,
            "sek": -0.59341,
            "sgd": 2.87854,
            "thb": 3.75737,
            "try": 11.26954,
            "twd": -1.32654,
            "uah": 6.20013,
            "usd": 5.40777,
            "vef": 5.40777,
            "vnd": 7.46592,
            "xag": 6.48351,
            "xau": -5.30183,
            "xdr": -0.48157,
            "xlm": 16.50941,
            "xrp": 17.59023,
            "yfi": 6.07968,
            "zar": 5.57882,
            "bits": -2.32783,
            "link": 16.84399,
            "sats": -2.32783
        },
        "price_change_percentage_200d_in_currency": {
            "aed": -39.52466,
            "ars": -27.51314,
            "aud": -37.44386,
            "bch": -38.48136,
            "bdt": -38.29885,
            "bhd": -39.36282,
            "bmd": -39.52391,
            "bnb": -38.90386,
            "brl": -39.49612,
            "btc": -57.16494,
            "cad": -39.31866,
            "chf": -42.10684,
            "clp": -38.89847,
            "cny": -38.02705,
            "czk": -42.63995,
            "dkk": -41.76504,
            "dot": -34.31283,
            "eos": -57.83052,
            "eth": -13.66772,
            "eur": -41.79039,
            "gbp": -40.70227,
            "gel": -39.08005,
            "hkd": -39.68313,
            "huf": -41.35973,
            "idr": -36.02679,
            "ils": -41.74062,
            "inr": -39.17535,
            "jpy": -41.43621,
            "krw": -37.9172,
            "kwd": -39.35573,
            "lkr": -37.97336,
            "ltc": -51.08953,
            "mmk": -39.52391,
            "mxn": -40.46623,
            "myr": -39.87593,
            "ngn": -40.54525,
            "nok": -42.32008,
            "nzd": -38.4052,
            "php": -41.88726,
            "pkr": -38.6197,
            "pln": -42.05197,
            "rub": -48.34808,
            "sar": -39.61923,
            "sek": -44.28237,
            "sgd": -40.06768,
            "thb": -39.746,
            "try": -31.93514,
            "twd": -42.30568,
            "uah": -38.96198,
            "usd": -39.52391,
            "vef": -39.52391,
            "vnd": -37.06923,
            "xag": -40.14149,
            "xau": -50.15501,
            "xdr": -41.71006,
            "xlm": -78.97487,
            "xrp": -84.90619,
            "yfi": -42.58657,
            "zar": -36.94793,
            "bits": -57.16494,
            "link": -52.26067,
            "sats": -57.16494
        },
        "price_change_percentage_1y_in_currency": {
            "aed": -60.51228,
            "ars": -47.14722,
            "aud": -59.53937,
            "bch": -48.42469,
            "bdt": -56.01899,
            "bhd": -60.37379,
            "bmd": -60.51336,
            "bnb": -60.36934,
            "brl": -55.94233,
            "btc": -73.61452,
            "cad": -60.08012,
            "chf": -63.91087,
            "clp": -60.20847,
            "cny": -60.19855,
            "czk": -62.59174,
            "dkk": -62.36842,
            "dot": -28.65108,
            "eos": -53.65227,
            "eth": -32.41073,
            "eur": -62.38001,
            "gbp": -62.65194,
            "gel": -59.40418,
            "hkd": -60.82597,
            "huf": -60.961,
            "idr": -59.28207,
            "ils": -61.55755,
            "inr": -59.9705,
            "jpy": -62.63905,
            "krw": -59.23634,
            "kwd": -60.48676,
            "lkr": -59.99088,
            "ltc": -62.43676,
            "mmk": -60.44011,
            "mxn": -54.43911,
            "myr": -64.4287,
            "ngn": -48.61204,
            "nok": -62.19346,
            "nzd": -60.12524,
            "php": -61.58835,
            "pkr": -60.0314,
            "pln": -62.81534,
            "rub": -64.60369,
            "sar": -60.51817,
            "sek": -64.66011,
            "sgd": -61.9817,
            "thb": -64.44359,
            "try": -53.05862,
            "twd": -62.44074,
            "uah": -58.24697,
            "usd": -60.51336,
            "vef": -60.51336,
            "vnd": -59.5986,
            "xag": -67.27814,
            "xau": -71.95021,
            "xdr": -62.42697,
            "xlm": -83.69427,
            "xrp": -90.35437,
            "yfi": -47.87704,
            "zar": -60.7587,
            "bits": -73.61452,
            "link": -60.12117,
            "sats": -73.61452
        },
        "market_cap_change_24h_in_currency": {
            "aed": -1341549.8581992984,
            "ars": -363223888.03637314,
            "aud": -566227.8453779258,
            "bch": 740.231,
            "bdt": -44492848.58994961,
            "bhd": -117774.22095873952,
            "bmd": -364990.3924826272,
            "bnb": -158.23842830804642,
            "brl": -2065736.124333933,
            "btc": -2.0857753625015505,
            "cad": -502591.17774862424,
            "chf": -302164.69105657935,
            "clp": -282463937.65649414,
            "cny": -2662604.9131608307,
            "czk": -8046833.685946763,
            "dkk": -2410519.5537175536,
            "dot": 85228,
            "eos": 915004,
            "eth": -161.5921827415732,
            "eur": -322925.2497490067,
            "gbp": -275121.7280647699,
            "gel": -1001898.6273647994,
            "hkd": -2820998.9646844566,
            "huf": -134255943.54328537,
            "idr": -6141904587.741516,
            "ils": -730598.6337179542,
            "inr": -32806865.36026597,
            "jpy": -54269845.092125416,
            "krw": -510058114.54400635,
            "kwd": -94644.30246567074,
            "lkr": -109619259.58969116,
            "ltc": -2734.5012657034677,
            "mmk": -765749843.4285507,
            "mxn": -7146694.7449964285,
            "myr": -1558508.9759008735,
            "ngn": -520428097.21712494,
            "nok": -3800243.467489749,
            "nzd": -613223.278333202,
            "php": -23137503.28605306,
            "pkr": -102890527.38780785,
            "pln": -1370973.4982915223,
            "rub": -25896531.740725756,
            "sar": -1370831.3914880008,
            "sek": -3523872.7423020005,
            "sgd": -474414.1471585408,
            "sol": -941.4137154878117,
            "thb": -12081181.991174817,
            "try": -16196801.336438417,
            "twd": -11210935.033388376,
            "uah": -15187221.396960735,
            "usd": -364990.3924826272,
            "vef": -36546.487999285106,
            "vnd": -9491575156.510681,
            "xag": -11387.817042383598,
            "xau": -112.60318598481444,
            "xdr": -262858.05087735504,
            "xlm": -492650.48065911233,
            "xrp": -111476.5658169305,
            "yfi": 89.537,
            "zar": -6713633.279325366,
            "bits": -2085775.3625015914,
            "link": 5252,
            "sats": -208577536.2501564
        },
        "market_cap_change_percentage_24h_in_currency": {
            "aed": -1.94247,
            "ars": -1.64821,
            "aud": -1.94114,
            "bch": 1.45644,
            "bdt": -1.94114,
            "bhd": -1.66218,
            "bmd": -1.94114,
            "bnb": -0.50403,
            "brl": -1.94114,
            "btc": -1.07003,
            "cad": -1.93404,
            "chf": -1.94303,
            "clp": -1.58773,
            "cny": -1.94114,
            "czk": -1.94114,
            "dkk": -1.94114,
            "dot": 1.87612,
            "eos": 3.61088,
            "eth": -1.57913,
            "eur": -1.94114,
            "gbp": -1.94114,
            "gel": -1.94114,
            "hkd": -1.93586,
            "huf": -1.99412,
            "idr": -1.98284,
            "ils": -1.08313,
            "inr": -2.06164,
            "jpy": -1.99189,
            "krw": -1.93781,
            "kwd": -1.6415,
            "lkr": -1.94114,
            "ltc": -1.26981,
            "mmk": -1.94114,
            "mxn": -1.94114,
            "myr": -1.94114,
            "ngn": -1.72587,
            "nok": -1.94114,
            "nzd": -1.94114,
            "php": -2.21067,
            "pkr": -1.94114,
            "pln": -1.92621,
            "rub": -1.66539,
            "sar": -1.94404,
            "sek": -1.94114,
            "sgd": -1.94114,
            "sol": -0.74441,
            "thb": -1.94114,
            "try": -2.23295,
            "twd": -1.94114,
            "uah": -1.94114,
            "usd": -1.94114,
            "vef": -1.94114,
            "vnd": -1.94114,
            "xag": -1.94114,
            "xau": -1.94114,
            "xdr": -1.94114,
            "xlm": -0.71665,
            "xrp": -1.31195,
            "yfi": 2.63494,
            "zar": -1.94114,
            "bits": -1.07003,
            "link": 0.40499,
            "sats": -1.07003
        },
        "total_supply": 1000000.0,
        "max_supply": 1000000.0,
        "max_supply_infinite": false,
        "circulating_supply": 754125.3679997192,
        "last_updated": "2025-05-04T15:24:59.551Z"
    },
    "community_data": {
        "facebook_likes": null,
        "twitter_followers": 198655,
        "reddit_average_posts_48h": 0.0,
        "reddit_average_comments_48h": 0.0,
        "reddit_subscribers": 0,
        "reddit_accounts_active_48h": 0,
        "telegram_channel_user_count": 16627
    },
    "developer_data": {
        "forks": 0,
        "stars": 0,
        "subscribers": 0,
        "total_issues": 0,
        "closed_issues": 0,
        "pull_requests_merged": 0,
        "pull_request_contributors": 0,
        "code_additions_deletions_4_weeks": {
            "additions": null,
            "deletions": null
        },
        "commit_count_4_weeks": 0,
        "last_4_weeks_commit_activity_series": []
    },
    "status_updates": [],
    "last_updated": "2025-05-04T15:24:59.551Z",
    "tickers": [
        {
            "base": "0X0D500B1D8E8EF31E21C99D1DB9A6444D3ADF1270",
            "target": "0X831753DD7087CAC61AB5644B308642CC1C33DC13",
            "market": {
                "name": "Quickswap",
                "identifier": "quickswap",
                "has_trading_incentive": false
            },
            "last": 0.009530281012,
            "volume": 4366.9371550772,
            "converted_last": {
                "btc": 0.00025539,
                "eth": 0.01333619,
                "usd": 24.42
            },
            "converted_volume": {
                "btc": 0.01053635,
                "eth": 0.55019285,
                "usd": 1007.49
            },
            "trust_score": "yellow",
            "bid_ask_spread_percentage": 0.605701,
            "timestamp": "2025-05-04T15:05:29+00:00",
            "last_traded_at": "2025-05-04T15:05:29+00:00",
            "last_fetch_at": "2025-05-04T15:22:32+00:00",
            "is_anomaly": false,
            "is_stale": false,
            "trade_url": "https://quickswap.exchange/#/swap?inputCurrency=0x0d500b1d8e8ef31e21c99d1db9a6444d3adf1270&outputCurrency=0x831753dd7087cac61ab5644b308642cc1c33dc13",
            "token_info_url": "https://info.quickswap.exchange/token/0x0d500b1d8e8ef31e21c99d1db9a6444d3adf1270",
            "coin_id": "wmatic",
            "target_coin_id": "quick"
        },
        {
            "base": "0X2791BCA1F2DE4661ED88A30C99A7A9449AA84174",
            "target": "0X831753DD7087CAC61AB5644B308642CC1C33DC13",
            "market": {
                "name": "Quickswap",
                "identifier": "quickswap",
                "has_trading_incentive": false
            },
            "last": 0.0409485029,
            "volume": 1141.026892,
            "converted_last": {
                "btc": 0.00025539,
                "eth": 0.01333619,
                "usd": 24.42
            },
            "converted_volume": {
                "btc": 0.01193371,
                "eth": 0.62316073,
                "usd": 1141.11
            },
            "trust_score": "yellow",
            "bid_ask_spread_percentage": 0.606077,
            "timestamp": "2025-05-04T15:20:27+00:00",
            "last_traded_at": "2025-05-04T15:20:27+00:00",
            "last_fetch_at": "2025-05-04T15:22:32+00:00",
            "is_anomaly": false,
            "is_stale": false,
            "trade_url": "https://quickswap.exchange/#/swap?inputCurrency=0x2791bca1f2de4661ed88a30c99a7a9449aa84174&outputCurrency=0x831753dd7087cac61ab5644b308642cc1c33dc13",
            "token_info_url": "https://info.quickswap.exchange/token/0x2791bca1f2de4661ed88a30c99a7a9449aa84174",
            "coin_id": "bridged-usdc-polygon-pos-bridge",
            "target_coin_id": "quick"
        },
        {
            "base": "0XB5C064F955D8E7F38FE0460C556A72987494EE17",
            "target": "0X831753DD7087CAC61AB5644B308642CC1C33DC13",
            "market": {
                "name": "Quickswap (v3)",
                "identifier": "quickswap_v3",
                "has_trading_incentive": false
            },
            "last": 0.0009583281662,
            "volume": 78840.0523466353,
            "converted_last": {
                "btc": 0.00025606,
                "eth": 0.01336752,
                "usd": 24.49
            },
            "converted_volume": {
                "btc": 0.01919649,
                "eth": 1.00216,
                "usd": 1835.66
            },
            "trust_score": "yellow",
            "bid_ask_spread_percentage": 0.615188,
            "timestamp": "2025-05-04T15:20:29+00:00",
            "last_traded_at": "2025-05-04T15:20:29+00:00",
            "last_fetch_at": "2025-05-04T15:20:29+00:00",
            "is_anomaly": false,
            "is_stale": false,
            "trade_url": "https://quickswap.exchange/#/swap?inputCurrency=0xb5c064f955d8e7f38fe0460c556a72987494ee17&outputCurrency=0x831753dd7087cac61ab5644b308642cc1c33dc13",
            "token_info_url": null,
            "coin_id": "quickswap",
            "target_coin_id": "quick"
        },
        {
            "base": "0X7CEB23FD6BC0ADD59E62AC25578270CFF1B9F619",
            "target": "0X831753DD7087CAC61AB5644B308642CC1C33DC13",
            "market": {
                "name": "Quickswap",
                "identifier": "quickswap",
                "has_trading_incentive": false
            },
            "last": 74.9963884003,
            "volume": 0.2870412176,
            "converted_last": {
                "btc": 0.00025539,
                "eth": 0.01333619,
                "usd": 24.42
            },
            "converted_volume": {
                "btc": 0.00549266,
                "eth": 0.28681839,
                "usd": 525.21
            },
            "trust_score": "yellow",
            "bid_ask_spread_percentage": 0.605897,
            "timestamp": "2025-05-04T15:11:29+00:00",
            "last_traded_at": "2025-05-04T15:11:29+00:00",
            "last_fetch_at": "2025-05-04T15:22:32+00:00",
            "is_anomaly": false,
            "is_stale": false,
            "trade_url": "https://quickswap.exchange/#/swap?inputCurrency=0x7ceb23fd6bc0add59e62ac25578270cff1b9f619&outputCurrency=0x831753dd7087cac61ab5644b308642cc1c33dc13",
            "token_info_url": "https://info.quickswap.exchange/token/0x7ceb23fd6bc0add59e62ac25578270cff1b9f619",
            "coin_id": "polygon-pos-bridged-weth-polygon-pos",
            "target_coin_id": "quick"
        },
        {
            "base": "0X8A953CFE442C5E8855CC6C61B1293FA648BAE472",
            "target": "0X831753DD7087CAC61AB5644B308642CC1C33DC13",
            "market": {
                "name": "Quickswap",
                "identifier": "quickswap",
                "has_trading_incentive": false
            },
            "last": 2.458448945e-10,
            "volume": 159963644930.557,
            "converted_last": {
                "btc": 0.00025596,
                "eth": 0.01336647,
                "usd": 24.49
            },
            "converted_volume": {
                "btc": 0.01080331,
                "eth": 0.56415279,
                "usd": 1033.57
            },
            "trust_score": "yellow",
            "bid_ask_spread_percentage": 0.650624,
            "timestamp": "2025-05-04T14:36:40+00:00",
            "last_traded_at": "2025-05-04T14:36:40+00:00",
            "last_fetch_at": "2025-05-04T15:18:20+00:00",
            "is_anomaly": false,
            "is_stale": false,
            "trade_url": "https://quickswap.exchange/#/swap?inputCurrency=0x8a953cfe442c5e8855cc6c61b1293fa648bae472&outputCurrency=0x831753dd7087cac61ab5644b308642cc1c33dc13",
            "token_info_url": "https://info.quickswap.exchange/token/0x8a953cfe442c5e8855cc6c61b1293fa648bae472",
            "coin_id": "polydoge",
            "target_coin_id": "quick"
        },
        {
            "base": "0XDF7837DE1F2FA4631D716CF2502F8B230F1DCC32",
            "target": "0X831753DD7087CAC61AB5644B308642CC1C33DC13",
            "market": {
                "name": "Quickswap",
                "identifier": "quickswap",
                "has_trading_incentive": false
            },
            "last": 0.0002320266082,
            "volume": 48702.38,
            "converted_last": {
                "btc": 0.00025529,
                "eth": 0.01333092,
                "usd": 24.41
            },
            "converted_volume": {
                "btc": 0.00286048,
                "eth": 0.14937008,
                "usd": 273.52
            },
            "trust_score": "yellow",
            "bid_ask_spread_percentage": 0.611376,
            "timestamp": "2025-05-04T15:15:33+00:00",
            "last_traded_at": "2025-05-04T15:15:33+00:00",
            "last_fetch_at": "2025-05-04T15:22:32+00:00",
            "is_anomaly": false,
            "is_stale": false,
            "trade_url": "https://quickswap.exchange/#/swap?inputCurrency=0xdf7837de1f2fa4631d716cf2502f8b230f1dcc32&outputCurrency=0x831753dd7087cac61ab5644b308642cc1c33dc13",
            "token_info_url": "https://info.quickswap.exchange/token/0x467bccd9d29f223bce8043b84e8c8b282827790f",
            "coin_id": "telcoin",
            "target_coin_id": "quick"
        },
        {
            "base": "0X385EEAC5CB85A38A9A07A70C73E0A3271CFB54A7",
            "target": "0X831753DD7087CAC61AB5644B308642CC1C33DC13",
            "market": {
                "name": "Quickswap",
                "identifier": "quickswap",
                "has_trading_incentive": false
            },
            "last": 0.01903778066,
            "volume": 777.1450158713,
            "converted_last": {
                "btc": 0.00025601,
                "eth": 0.01336532,
                "usd": 24.48
            },
            "converted_volume": {
                "btc": 0.00384973,
                "eth": 0.20097652,
                "usd": 368.13
            },
            "trust_score": "yellow",
            "bid_ask_spread_percentage": 0.623306,
            "timestamp": "2025-05-04T14:26:22+00:00",
            "last_traded_at": "2025-05-04T14:26:22+00:00",
            "last_fetch_at": "2025-05-04T15:20:26+00:00",
            "is_anomaly": false,
            "is_stale": false,
            "trade_url": "https://quickswap.exchange/#/swap?inputCurrency=0x385eeac5cb85a38a9a07a70c73e0a3271cfb54a7&outputCurrency=0x831753dd7087cac61ab5644b308642cc1c33dc13",
            "token_info_url": "https://info.quickswap.exchange/token/0x3f382dbd960e3a9bbceae22651e88158d2791550",
            "coin_id": "aavegotchi",
            "target_coin_id": "quick"
        },
        {
            "base": "0XC3EC80343D2BAE2F8E680FDADDE7C17E71E114EA",
            "target": "0X831753DD7087CAC61AB5644B308642CC1C33DC13",
            "market": {
                "name": "Quickswap",
                "identifier": "quickswap",
                "has_trading_incentive": false
            },
            "last": 0.01656471056,
            "volume": 357.1249834111,
            "converted_last": {
                "btc": 0.00025507,
                "eth": 0.01331967,
                "usd": 24.4
            },
            "converted_volume": {
                "btc": 0.00154392,
                "eth": 0.08062402,
                "usd": 147.71
            },
            "trust_score": "yellow",
            "bid_ask_spread_percentage": 0.668853,
            "timestamp": "2025-05-04T13:44:14+00:00",
            "last_traded_at": "2025-05-04T13:44:14+00:00",
            "last_fetch_at": "2025-05-04T15:18:20+00:00",
            "is_anomaly": false,
            "is_stale": false,
            "trade_url": "https://quickswap.exchange/#/swap?inputCurrency=0xc3ec80343d2bae2f8e680fdadde7c17e71e114ea&outputCurrency=0x831753dd7087cac61ab5644b308642cc1c33dc13",
            "token_info_url": "https://info.quickswap.exchange/token/0x3593d125a4f7849a1b059e64f4517a86dd60c95d",
            "coin_id": "mantra-dao",
            "target_coin_id": "quick"
        },
        {
            "base": "0X53E0BCA35EC356BD5DDDFEBBD1FC0FD03FABAD39",
            "target": "0X831753DD7087CAC61AB5644B308642CC1C33DC13",
            "market": {
                "name": "Quickswap",
                "identifier": "quickswap",
                "has_trading_incentive": false
            },
            "last": 0.5780902292,
            "volume": 4.207455025,
            "converted_last": {
                "btc": 0.00025507,
                "eth": 0.01331967,
                "usd": 24.4
            },
            "converted_volume": {
                "btc": 0.00062484,
                "eth": 0.03262918,
                "usd": 59.78
            },
            "trust_score": "yellow",
            "bid_ask_spread_percentage": 0.665866,
            "timestamp": "2025-05-04T14:06:44+00:00",
            "last_traded_at": "2025-05-04T14:06:44+00:00",
            "last_fetch_at": "2025-05-04T15:18:18+00:00",
            "is_anomaly": false,
            "is_stale": false,
            "trade_url": "https://quickswap.exchange/#/swap?inputCurrency=0x53e0bca35ec356bd5dddfebbd1fc0fd03fabad39&outputCurrency=0x831753dd7087cac61ab5644b308642cc1c33dc13",
            "token_info_url": "https://info.quickswap.exchange/token/0x514910771af9ca656af840dff83e8264ecf986ca",
            "coin_id": "chainlink",
            "target_coin_id": "quick"
        },
        {
            "base": "0X6C28AEF8977C9B773996D0E8376D2EE379446F2F",
            "target": "0XC02AAA39B223FE8D0A0E5C4F27EAD9083C756CC2",
            "market": {
                "name": "Uniswap V2 (Ethereum)",
                "identifier": "uniswap_v2",
                "has_trading_incentive": false
            },
            "last": 0.01319904009,
            "volume": 2.0825139729,
            "converted_last": {
                "btc": 0.00025276,
                "eth": 0.01319764,
                "usd": 24.17
            },
            "converted_volume": {
                "btc": 0.00053316,
                "eth": 0.02783834,
                "usd": 50.98
            },
            "trust_score": "yellow",
            "bid_ask_spread_percentage": 0.700076,
            "timestamp": "2025-05-04T10:33:31+00:00",
            "last_traded_at": "2025-05-04T10:33:31+00:00",
            "last_fetch_at": "2025-05-04T15:21:56+00:00",
            "is_anomaly": false,
            "is_stale": false,
            "trade_url": "https://app.uniswap.org/explore/tokens/ethereum/0x6c28aef8977c9b773996d0e8376d2ee379446f2f",
            "token_info_url": "https://v2.info.uniswap.org/token/0x6c28aef8977c9b773996d0e8376d2ee379446f2f",
            "coin_id": "quick",
            "target_coin_id": "weth"
        },
        {
            "base": "0XB33EAAD8D922B1083446DC23F610C2567FB5180F",
            "target": "0X831753DD7087CAC61AB5644B308642CC1C33DC13",
            "market": {
                "name": "Quickswap",
                "identifier": "quickswap",
                "has_trading_incentive": false
            },
            "last": 0.2085884151,
            "volume": 3.2280852144,
            "converted_last": {
                "btc": 0.00025507,
                "eth": 0.01331967,
                "usd": 24.4
            },
            "converted_volume": {
                "btc": 0.00017059,
                "eth": 0.00890813,
                "usd": 16.32
            },
            "trust_score": "yellow",
            "bid_ask_spread_percentage": 0.797511,
            "timestamp": "2025-05-04T13:08:30+00:00",
            "last_traded_at": "2025-05-04T13:08:30+00:00",
            "last_fetch_at": "2025-05-04T15:18:20+00:00",
            "is_anomaly": false,
            "is_stale": false,
            "trade_url": "https://quickswap.exchange/#/swap?inputCurrency=0xb33eaad8d922b1083446dc23f610c2567fb5180f&outputCurrency=0x831753dd7087cac61ab5644b308642cc1c33dc13",
            "token_info_url": "https://info.quickswap.exchange/token/0x1f9840a85d5af5bf1d1762f925bdaddc4201f984",
            "coin_id": "uniswap",
            "target_coin_id": "quick"
        },
        {
            "base": "0X1B815D120B3EF02039EE11DC2D33DE7AA4A8C603",
            "target": "0X831753DD7087CAC61AB5644B308642CC1C33DC13",
            "market": {
                "name": "Quickswap",
                "identifier": "quickswap",
                "has_trading_incentive": false
            },
            "last": 0.002911579385,
            "volume": 157.4888587587,
            "converted_last": {
                "btc": 0.00025507,
                "eth": 0.01331967,
                "usd": 24.4
            },
            "converted_volume": {
                "btc": 0.00011825,
                "eth": 0.00617521,
                "usd": 11.31
            },
            "trust_score": "yellow",
            "bid_ask_spread_percentage": 0.883416,
            "timestamp": "2025-05-04T13:20:32+00:00",
            "last_traded_at": "2025-05-04T13:20:32+00:00",
            "last_fetch_at": "2025-05-04T15:18:18+00:00",
            "is_anomaly": false,
            "is_stale": false,
            "trade_url": "https://quickswap.exchange/#/swap?inputCurrency=0x1b815d120b3ef02039ee11dc2d33de7aa4a8c603&outputCurrency=0x831753dd7087cac61ab5644b308642cc1c33dc13",
            "token_info_url": "https://info.quickswap.exchange/token/0x4691937a7508860f876c9c0a2a617e7d9e945d4b",
            "coin_id": "woo-network",
            "target_coin_id": "quick"
        },
        {
            "base": "0XAB0B2DDB9C7E440FAC8E140A89C0DBCBF2D7BBFF",
            "target": "0X831753DD7087CAC61AB5644B308642CC1C33DC13",
            "market": {
                "name": "Quickswap",
                "identifier": "quickswap",
                "has_trading_incentive": false
            },
            "last": 1.9736034562,
            "volume": 0.536185436,
            "converted_last": {
                "btc": 0.00025541,
                "eth": 0.01333634,
                "usd": 24.42
            },
            "converted_volume": {
                "btc": 0.00026818,
                "eth": 0.01400284,
                "usd": 25.64
            },
            "trust_score": "red",
            "bid_ask_spread_percentage": 0.632924,
            "timestamp": "2025-05-04T12:34:27+00:00",
            "last_traded_at": "2025-05-04T12:34:27+00:00",
            "last_fetch_at": "2025-05-04T15:21:17+00:00",
            "is_anomaly": false,
            "is_stale": false,
            "trade_url": "https://quickswap.exchange/#/swap?inputCurrency=0xab0b2ddb9c7e440fac8e140a89c0dbcbf2d7bbff&outputCurrency=0x831753dd7087cac61ab5644b308642cc1c33dc13",
            "token_info_url": "https://info.quickswap.exchange/token/0x1571ed0bed4d987fe2b498ddbae7dfa19519f651",
            "coin_id": "ifarm",
            "target_coin_id": "quick"
        },
        {
            "base": "0X70C006878A5A50ED185AC4C87D837633923DE296",
            "target": "0X831753DD7087CAC61AB5644B308642CC1C33DC13",
            "market": {
                "name": "Quickswap",
                "identifier": "quickswap",
                "has_trading_incentive": false
            },
            "last": 4.865049624e-05,
            "volume": 14190.0919497234,
            "converted_last": {
                "btc": 0.00025507,
                "eth": 0.01331967,
                "usd": 24.4
            },
            "converted_volume": {
                "btc": 0.00017473,
                "eth": 0.00912446,
                "usd": 16.72
            },
            "trust_score": "red",
            "bid_ask_spread_percentage": 0.707059,
            "timestamp": "2025-05-04T11:11:54+00:00",
            "last_traded_at": "2025-05-04T11:11:54+00:00",
            "last_fetch_at": "2025-05-04T15:18:18+00:00",
            "is_anomaly": false,
            "is_stale": false,
            "trade_url": "https://quickswap.exchange/#/swap?inputCurrency=0x70c006878a5a50ed185ac4c87d837633923de296&outputCurrency=0x831753dd7087cac61ab5644b308642cc1c33dc13",
            "token_info_url": "https://info.quickswap.exchange/token/0x557b933a7c2c45672b610f8954a3deb39a51a8ca",
            "coin_id": "revv",
            "target_coin_id": "quick"
        },
        {
            "base": "0XE82808EAA78339B06A691FD92E1BE79671CAD8D3",
            "target": "0X831753DD7087CAC61AB5644B308642CC1C33DC13",
            "market": {
                "name": "Quickswap",
                "identifier": "quickswap",
                "has_trading_incentive": false
            },
            "last": 0.0001550061567,
            "volume": 1881.58872973,
            "converted_last": {
                "btc": 0.00025566,
                "eth": 0.0133509,
                "usd": 24.46
            },
            "converted_volume": {
                "btc": 7.445e-05,
                "eth": 0.00388793,
                "usd": 7.12
            },
            "trust_score": "red",
            "bid_ask_spread_percentage": 0.700166,
            "timestamp": "2025-05-04T12:03:21+00:00",
            "last_traded_at": "2025-05-04T12:03:21+00:00",
            "last_fetch_at": "2025-05-04T15:18:18+00:00",
            "is_anomaly": false,
            "is_stale": false,
            "trade_url": "https://quickswap.exchange/#/swap?inputCurrency=0xe82808eaa78339b06a691fd92e1be79671cad8d3&outputCurrency=0x831753dd7087cac61ab5644b308642cc1c33dc13",
            "token_info_url": "https://info.quickswap.exchange/token/0x72f020f8f3e8fd9382705723cd26380f8d0c66bb",
            "coin_id": "plotx",
            "target_coin_id": "quick"
        },
        {
            "base": "0X823CD4264C1B951C9209AD0DEAEA9988FE8429BF",
            "target": "0X831753DD7087CAC61AB5644B308642CC1C33DC13",
            "market": {
                "name": "Quickswap",
                "identifier": "quickswap",
                "has_trading_incentive": false
            },
            "last": 6.4513304462,
            "volume": 0.03670250964,
            "converted_last": {
                "btc": 0.00025507,
                "eth": 0.01331967,
                "usd": 24.4
            },
            "converted_volume": {
                "btc": 6.032e-05,
                "eth": 0.00315005,
                "usd": 5.77
            },
            "trust_score": "red",
            "bid_ask_spread_percentage": 0.699006,
            "timestamp": "2025-05-04T11:06:23+00:00",
            "last_traded_at": "2025-05-04T11:06:23+00:00",
            "last_fetch_at": "2025-05-04T15:18:18+00:00",
            "is_anomaly": false,
            "is_stale": false,
            "trade_url": "https://quickswap.exchange/#/swap?inputCurrency=0x823cd4264c1b951c9209ad0deaea9988fe8429bf&outputCurrency=0x831753dd7087cac61ab5644b308642cc1c33dc13",
            "token_info_url": "https://info.quickswap.exchange/token/0x823cd4264c1b951c9209ad0deaea9988fe8429bf",
            "coin_id": "matic-aave-aave",
            "target_coin_id": "quick"
        },
        {
            "base": "0X23D29D30E35C5E8D321E1DC9A8A61BFD846D4C5C",
            "target": "0X831753DD7087CAC61AB5644B308642CC1C33DC13",
            "market": {
                "name": "Quickswap",
                "identifier": "quickswap",
                "has_trading_incentive": false
            },
            "last": 7.983483013e-05,
            "volume": 5381.95632754,
            "converted_last": {
                "btc": 0.00025507,
                "eth": 0.01331967,
                "usd": 24.4
            },
            "converted_volume": {
                "btc": 0.00011085,
                "eth": 0.00578838,
                "usd": 10.6
            },
            "trust_score": "red",
            "bid_ask_spread_percentage": 0.858671,
            "timestamp": "2025-05-04T10:24:21+00:00",
            "last_traded_at": "2025-05-04T10:24:21+00:00",
            "last_fetch_at": "2025-05-04T15:18:18+00:00",
            "is_anomaly": false,
            "is_stale": false,
            "trade_url": "https://quickswap.exchange/#/swap?inputCurrency=0x23d29d30e35c5e8d321e1dc9a8a61bfd846d4c5c&outputCurrency=0x831753dd7087cac61ab5644b308642cc1c33dc13",
            "token_info_url": "https://info.quickswap.exchange/token/0x2b591e99afe9f32eaa6214f7b7629768c40eeb39",
            "coin_id": "hex",
            "target_coin_id": "quick"
        },
        {
            "base": "0X04B33078EA1AEF29BF3FB29C6AB7B200C58EA126",
            "target": "0X831753DD7087CAC61AB5644B308642CC1C33DC13",
            "market": {
                "name": "Quickswap",
                "identifier": "quickswap",
                "has_trading_incentive": false
            },
            "last": 4.238337821e-05,
            "volume": 3971.3771181613,
            "converted_last": {
                "btc": 0.0002537,
                "eth": 0.01324853,
                "usd": 24.27
            },
            "converted_volume": {
                "btc": 4.243e-05,
                "eth": 0.00221565,
                "usd": 4.06
            },
            "trust_score": "red",
            "bid_ask_spread_percentage": 0.848118,
            "timestamp": "2025-05-04T12:03:21+00:00",
            "last_traded_at": "2025-05-04T12:03:21+00:00",
            "last_fetch_at": "2025-05-04T15:18:18+00:00",
            "is_anomaly": false,
            "is_stale": false,
            "trade_url": "https://quickswap.exchange/#/swap?inputCurrency=0x04b33078ea1aef29bf3fb29c6ab7b200c58ea126&outputCurrency=0x831753dd7087cac61ab5644b308642cc1c33dc13",
            "token_info_url": "https://info.quickswap.exchange/token/0x04b33078ea1aef29bf3fb29c6ab7b200c58ea126",
            "coin_id": "safle",
            "target_coin_id": "quick"
        },
        {
            "base": "0XC004E2318722EA2B15499D6375905D75EE5390B8",
            "target": "0X831753DD7087CAC61AB5644B308642CC1C33DC13",
            "market": {
                "name": "Quickswap",
                "identifier": "quickswap",
                "has_trading_incentive": false
            },
            "last": 3.236047236e-05,
            "volume": 6129.74830976,
            "converted_last": {
                "btc": 0.0002533,
                "eth": 0.01322762,
                "usd": 24.23
            },
            "converted_volume": {
                "btc": 5.021e-05,
                "eth": 0.00262218,
                "usd": 4.8
            },
            "trust_score": "red",
            "bid_ask_spread_percentage": 0.885707,
            "timestamp": "2025-05-04T10:54:09+00:00",
            "last_traded_at": "2025-05-04T10:54:09+00:00",
            "last_fetch_at": "2025-05-04T15:18:18+00:00",
            "is_anomaly": false,
            "is_stale": false,
            "trade_url": "https://quickswap.exchange/#/swap?inputCurrency=0xc004e2318722ea2b15499d6375905d75ee5390b8&outputCurrency=0x831753dd7087cac61ab5644b308642cc1c33dc13",
            "token_info_url": "https://info.quickswap.exchange/token/0xc004e2318722ea2b15499d6375905d75ee5390b8",
            "coin_id": "kommunitas",
            "target_coin_id": "quick"
        },
        {
            "base": "0X6968105460F67C3BF751BE7C15F92F5286FD0CE5",
            "target": "0X831753DD7087CAC61AB5644B308642CC1C33DC13",
            "market": {
                "name": "Quickswap",
                "identifier": "quickswap",
                "has_trading_incentive": false
            },
            "last": 1.0094389138,
            "volume": 0.2416773716,
            "converted_last": {
                "btc": 0.00025309,
                "eth": 0.01321672,
                "usd": 24.21
            },
            "converted_volume": {
                "btc": 6.14e-05,
                "eth": 0.00320646,
                "usd": 5.87
            },
            "trust_score": null,
            "bid_ask_spread_percentage": 0.726427,
            "timestamp": "2025-05-04T13:26:11+00:00",
            "last_traded_at": "2025-05-04T13:26:11+00:00",
            "last_fetch_at": "2025-05-04T15:18:18+00:00",
            "is_anomaly": false,
            "is_stale": false,
            "trade_url": "https://quickswap.exchange/#/swap?inputCurrency=0x6968105460f67c3bf751be7c15f92f5286fd0ce5&outputCurrency=0x831753dd7087cac61ab5644b308642cc1c33dc13",
            "token_info_url": "https://info.quickswap.exchange/token/0x275f5ad03be0fa221b4c6649b8aee09a42d9412a",
            "coin_id": "monavale",
            "target_coin_id": "quick"
        },
        {
            "base": "0X51869836681BCE74A514625C856AFB697A013797",
            "target": "0X831753DD7087CAC61AB5644B308642CC1C33DC13",
            "market": {
                "name": "Quickswap",
                "identifier": "quickswap",
                "has_trading_incentive": false
            },
            "last": 1.644034763e-05,
            "volume": 15505.9931259728,
            "converted_last": {
                "btc": 0.00025721,
                "eth": 0.01350543,
                "usd": 24.81
            },
            "converted_volume": {
                "btc": 6.513e-05,
                "eth": 0.00342005,
                "usd": 6.28
            },
            "trust_score": "yellow",
            "bid_ask_spread_percentage": 0.852746,
            "timestamp": "2025-05-03T14:33:15+00:00",
            "last_traded_at": "2025-05-03T14:33:15+00:00",
            "last_fetch_at": "2025-05-03T15:33:19+00:00",
            "is_anomaly": false,
            "is_stale": true,
            "trade_url": "https://quickswap.exchange/#/swap?inputCurrency=0x51869836681bce74a514625c856afb697a013797&outputCurrency=0x831753dd7087cac61ab5644b308642cc1c33dc13",
            "token_info_url": "https://info.quickswap.exchange/token/0x51869836681bce74a514625c856afb697a013797",
            "coin_id": "genesis-worlds",
            "target_coin_id": "quick"
        },
        {
            "base": "0X6CCF12B480A99C54B23647C995F4525D544A7E72",
            "target": "0X831753DD7087CAC61AB5644B308642CC1C33DC13",
            "market": {
                "name": "Quickswap",
                "identifier": "quickswap",
                "has_trading_incentive": false
            },
            "last": 0.00106281084,
            "volume": 57.5178892935,
            "converted_last": {
                "btc": 0.00026132,
                "eth": 0.01372855,
                "usd": 25.37
            },
            "converted_volume": {
                "btc": 1.597e-05,
                "eth": 0.00083923,
                "usd": 1.55
            },
            "trust_score": "red",
            "bid_ask_spread_percentage": 0.724605,
            "timestamp": "2025-05-01T12:33:30+00:00",
            "last_traded_at": "2025-05-01T12:33:30+00:00",
            "last_fetch_at": "2025-05-02T01:30:10+00:00",
            "is_anomaly": false,
            "is_stale": true,
            "trade_url": "https://quickswap.exchange/#/swap?inputCurrency=0x6ccf12b480a99c54b23647c995f4525d544a7e72&outputCurrency=0x831753dd7087cac61ab5644b308642cc1c33dc13",
            "token_info_url": "https://info.quickswap.exchange/token/0x31d0a7ada4d4c131eb612db48861211f63e57610",
            "coin_id": "bscstarter",
            "target_coin_id": "quick"
        },
        {
            "base": "0X6AB6D61428FDE76768D7B45D8BFEEC19C6EF91A8",
            "target": "0X831753DD7087CAC61AB5644B308642CC1C33DC13",
            "market": {
                "name": "Quickswap",
                "identifier": "quickswap",
                "has_trading_incentive": false
            },
            "last": 0.03420892289,
            "volume": 3.9259387501,
            "converted_last": {
                "btc": 0.00025507,
                "eth": 0.01331967,
                "usd": 24.4
            },
            "converted_volume": {
                "btc": 3.416e-05,
                "eth": 0.00178389,
                "usd": 3.27
            },
            "trust_score": "red",
            "bid_ask_spread_percentage": 0.752454,
            "timestamp": "2025-05-04T03:56:59+00:00",
            "last_traded_at": "2025-05-04T03:56:59+00:00",
            "last_fetch_at": "2025-05-04T15:18:17+00:00",
            "is_anomaly": false,
            "is_stale": true,
            "trade_url": "https://quickswap.exchange/#/swap?inputCurrency=0x6ab6d61428fde76768d7b45d8bfeec19c6ef91a8&outputCurrency=0x831753dd7087cac61ab5644b308642cc1c33dc13",
            "token_info_url": "https://info.quickswap.exchange/token/0xddcb3ffd12750b45d32e084887fdf1aabab34239",
            "coin_id": "anyswap",
            "target_coin_id": "quick"
        },
        {
            "base": "0XF28164A485B0B2C90639E47B0F377B4A438A16B1",
            "target": "0X831753DD7087CAC61AB5644B308642CC1C33DC13",
            "market": {
                "name": "Quickswap",
                "identifier": "quickswap",
                "has_trading_incentive": false
            },
            "last": 1.7178837485,
            "volume": 0.03258209881,
            "converted_last": {
                "btc": 0.00026746,
                "eth": 0.01403138,
                "usd": 25.47
            },
            "converted_volume": {
                "btc": 1.501e-05,
                "eth": 0.00078747,
                "usd": 1.43
            },
            "trust_score": "red",
            "bid_ask_spread_percentage": 0.973721,
            "timestamp": "2025-04-30T09:35:25+00:00",
            "last_traded_at": "2025-04-30T09:35:25+00:00",
            "last_fetch_at": "2025-04-30T12:00:26+00:00",
            "is_anomaly": true,
            "is_stale": true,
            "trade_url": "https://quickswap.exchange/#/swap?inputCurrency=0xf28164a485b0b2c90639e47b0f377b4a438a16b1&outputCurrency=0x831753dd7087cac61ab5644b308642cc1c33dc13",
            "token_info_url": "https://info.quickswap.exchange/token/0xf28164a485b0b2c90639e47b0f377b4a438a16b1",
            "coin_id": "dragons-quick",
            "target_coin_id": "quick"
        }
    ]
}